unicode_raw_input.py
unicode_raw_input-0.1.0a0.dist-info/licenses/LICENSE
unicode_raw_input-0.1.0a0.dist-info/METADATA
unicode_raw_input-0.1.0a0.dist-info/WHEEL
unicode_raw_input-0.1.0a0.dist-info/top_level.txt
unicode_raw_input-0.1.0a0.dist-info/RECORD
