Metadata-Version: 2.4
Name: unicode-raw-input
Version: 0.1.0a0
Summary: A cross-platform Unicode-aware replacement for Python's `raw_input()` (Python 2) and `input()` (Python 3) that handles Unicode text consistently across Python versions and operating systems.
Author-email: Jifeng Wu <jifengwu2k@gmail.com>
License-Expression: MIT
Project-URL: Homepage, https://github.com/jifengwu2k/unicode-raw-input
Project-URL: Bug Tracker, https://github.com/jifengwu2k/unicode-raw-input/issues
Classifier: Programming Language :: Python :: 2
Classifier: Programming Language :: Python :: 3
Classifier: Operating System :: OS Independent
Requires-Python: >=2
License-File: LICENSE
Requires-Dist: textcompat
Requires-Dist: typing; python_version < "3.5"
Dynamic: license-file
